xhydro_temp/__init__.py
xhydro_temp/cc.py
xhydro_temp/gis.py
xhydro_temp/indicators.py
xhydro_temp/utils.py
xhydro_temp/extreme_value_analysis/Extremes_playground.ipynb
xhydro_temp/extreme_value_analysis/__init__.py
xhydro_temp/extreme_value_analysis/conversions_example.ipynb
xhydro_temp/extreme_value_analysis/debug.ipynb
xhydro_temp/extreme_value_analysis/julia_import.py
xhydro_temp/extreme_value_analysis/parameterestimation.py
xhydro_temp/extreme_value_analysis/xclim_example.ipynb
xhydro_temp/extreme_value_analysis/.ipynb_checkpoints/Extremes_playground-checkpoint.ipynb
xhydro_temp/extreme_value_analysis/.ipynb_checkpoints/Untitled-checkpoint.ipynb
xhydro_temp/extreme_value_analysis/structures/conversions.py
xhydro_temp/extreme_value_analysis/structures/dataitem.py
xhydro_temp/extreme_value_analysis/structures/util.py
xhydro_temp/frequency_analysis/__init__.py
xhydro_temp/frequency_analysis/local.py
xhydro_temp/modelling/__init__.py
xhydro_temp/modelling/_hm.py
xhydro_temp/modelling/_hydrotel.py
xhydro_temp/modelling/_simplemodels.py
xhydro_temp/modelling/calibration.py
xhydro_temp/modelling/hydrological_modelling.py
xhydro_temp/modelling/obj_funcs.py
xhydro_temp/modelling/data/hydrotel_defaults/output.csv
xhydro_temp/modelling/data/hydrotel_defaults/project.csv
xhydro_temp/modelling/data/hydrotel_defaults/simulation.csv
xhydro_temp/optimal_interpolation/ECF_climate_correction.py
xhydro_temp/optimal_interpolation/__init__.py
xhydro_temp/optimal_interpolation/compare_result.py
xhydro_temp/optimal_interpolation/optimal_interpolation_fun.py
xhydro_temp/optimal_interpolation/utilities.py
xhydro_temp/testing/__init__.py
xhydro_temp/testing/helpers.py
xhydro_temp/testing/registry.txt
xhydro_temp/testing/utils.py
xhydro_temp-0.3.8.dev4.dist-info/LICENSE
xhydro_temp-0.3.8.dev4.dist-info/WHEEL
xhydro_temp-0.3.8.dev4.dist-info/METADATA
xhydro_temp-0.3.8.dev4.dist-info/RECORD
