Metadata-Version: 2.1
Name: xhydro_temp
Version: 0.3.8.dev4
Summary: Hydrological analysis library built with xarray.
Keywords: xhydro
Author: Sébastien Langlois
Author-email: Thomas-Charles Fortier Filion <tcff_hydro@outlook.com>, Gabriel Rondeau-Genesse <rondeau-genesse.gabriel@ouranos.ca>
Maintainer-email: Trevor James Smith <smith.trevorj@ouranos.ca>, Gabriel Rondeau-Genesse <rondeau-genesse.gabriel@ouranos.ca>
Requires-Python: >=3.9.0
Classifier: Development Status :: 3 - Alpha
Classifier: Intended Audience :: Developers
Classifier: Intended Audience :: Science/Research
Classifier: License :: OSI Approved :: Apache Software License
Classifier: Natural Language :: English
Classifier: Operating System :: OS Independent
Classifier: Programming Language :: Python :: 3
Classifier: Programming Language :: Python :: 3 :: Only
Classifier: Programming Language :: Python :: 3.9
Classifier: Programming Language :: Python :: 3.10
Classifier: Programming Language :: Python :: 3.11
Classifier: Programming Language :: Python :: 3.12
Classifier: Programming Language :: Python :: Implementation :: CPython
Classifier: Topic :: Scientific/Engineering :: GIS
Classifier: Topic :: Scientific/Engineering :: Hydrology
Requires-Dist: cartopy
Requires-Dist: geopandas
Requires-Dist: haversine
Requires-Dist: intake <2.0.0
Requires-Dist: intake-esm !=2024.2.6
Requires-Dist: leafmap
Requires-Dist: numpy <2.0.0
Requires-Dist: pandas
Requires-Dist: planetary-computer
Requires-Dist: pooch >=1.8.0
Requires-Dist: pydantic >=2.0,<2.5.3
Requires-Dist: pystac
Requires-Dist: pystac-client
Requires-Dist: pyyaml
Requires-Dist: rasterio
Requires-Dist: ravenpy >=0.15.0
Requires-Dist: rioxarray
Requires-Dist: spotpy
Requires-Dist: stackstac
Requires-Dist: statsmodels
Requires-Dist: tqdm
Requires-Dist: xarray>=2023.11.0
Requires-Dist: xarray-spatial
Requires-Dist: xclim>=0.48.2
Requires-Dist: xdatasets>=0.3.5
Requires-Dist: xscen>=0.8.3
Requires-Dist: xvec
Requires-Dist: xhydro[dev] ; extra == "all"
Requires-Dist: xhydro[docs] ; extra == "all"
Requires-Dist: pip >=23.3.0 ; extra == "dev"
Requires-Dist: bump-my-version >=0.18.3 ; extra == "dev"
Requires-Dist: watchdog >=3.0.0 ; extra == "dev"
Requires-Dist: flake8 >=7.0.0 ; extra == "dev"
Requires-Dist: flake8-alphabetize >=0.0.21 ; extra == "dev"
Requires-Dist: flake8-rst-docstrings >=0.3.0 ; extra == "dev"
Requires-Dist: flit >=3.9.0 ; extra == "dev"
Requires-Dist: tox >=4.5.1 ; extra == "dev"
Requires-Dist: coverage >=7.0.0 ; extra == "dev"
Requires-Dist: coveralls >=4.0.0 ; extra == "dev"
Requires-Dist: mypy ; extra == "dev"
Requires-Dist: pytest >=7.3.1 ; extra == "dev"
Requires-Dist: pytest-cov >=4.0.0 ; extra == "dev"
Requires-Dist: black ==24.4.2 ; extra == "dev"
Requires-Dist: blackdoc ==0.3.9 ; extra == "dev"
Requires-Dist: isort ==5.13.2 ; extra == "dev"
Requires-Dist: pre-commit >=3.3.2 ; extra == "dev"
Requires-Dist: ruff >=0.3.0 ; extra == "dev"
Requires-Dist: furo ; extra == "docs"
Requires-Dist: hvplot ; extra == "docs"
Requires-Dist: ipykernel ; extra == "docs"
Requires-Dist: ipython ; extra == "docs"
Requires-Dist: jupyter_client ; extra == "docs"
Requires-Dist: nbsphinx ; extra == "docs"
Requires-Dist: nbval ; extra == "docs"
Requires-Dist: sphinx ; extra == "docs"
Requires-Dist: sphinx-autoapi ; extra == "docs"
Requires-Dist: sphinx-codeautolink ; extra == "docs"
Requires-Dist: sphinx-copybutton ; extra == "docs"
Requires-Dist: sphinx-intl ; extra == "docs"
Requires-Dist: sphinxcontrib-napoleon ; extra == "docs"
Requires-Dist: xagg ; extra == "docs"
Project-URL: Changelog, https://xhydro.readthedocs.io/en/stable/changelog.html
Project-URL: Homepage, https://xhydro.readthedocs.io/
Project-URL: Issue tracker, https://github.com/hydrologie/xhydro/issues
Project-URL: Source, https://github.com/hydrologie/xhydro
Provides-Extra: all
Provides-Extra: dev
Provides-Extra: docs
